[1,["1e40d7fb7@6c48a"],["_textureSource"],["cc.SpriteFrame"],0,[[[{"name":"boards","rect":{"x":470,"y":3,"width":300,"height":300},"offset":{"x":0,"y":0},"originalSize":{"width":300,"height":300},"rotated":false,"capInsets":[0,0,0,0],"packable":true,"pixelsToUnit":100,"pivot":{"x":0.5,"y":0.5},"meshType":0}],[0],0,[0],[0],[0]],[[{"name":"30","rect":{"x":756,"y":474,"width":252,"height":240},"offset":{"x":1,"y":-2},"originalSize":{"width":256,"height":248},"rotated":false,"capInsets":[0,0,0,0],"packable":true,"pixelsToUnit":100,"pivot":{"x":0.5,"y":0.5},"meshType":0}],[0],0,[0],[0],[0]],[[{"name":"42","rect":{"x":776,"y":3,"width":222,"height":245},"offset":{"x":8,"y":1.5},"originalSize":{"width":256,"height":248},"rotated":true,"capInsets":[0,0,0,0],"packable":true,"pixelsToUnit":100,"pivot":{"x":0.5,"y":0.5},"meshType":0}],[0],0,[0],[0],[0]],[[{"name":"23","rect":{"x":684,"y":761,"width":241,"height":233},"offset":{"x":-0.5,"y":7.5},"originalSize":{"width":256,"height":248},"rotated":true,"capInsets":[0,0,0,0],"packable":true,"pixelsToUnit":100,"pivot":{"x":0.5,"y":0.5},"meshType":0}],[0],0,[0],[0],[0]],[[{"name":"43","rect":{"x":221,"y":764,"width":217,"height":244},"offset":{"x":10.5,"y":2},"originalSize":{"width":256,"height":248},"rotated":false,"capInsets":[0,0,0,0],"packable":true,"pixelsToUnit":100,"pivot":{"x":0.5,"y":0.5},"meshType":0}],[0],0,[0],[0],[0]],[[{"name":"item_8","rect":{"x":923,"y":922,"width":93,"height":98},"offset":{"x":-0.5,"y":-3},"originalSize":{"width":120,"height":120},"rotated":true,"capInsets":[0,0,0,0],"packable":true,"pixelsToUnit":100,"pivot":{"x":0.5,"y":0.5},"meshType":0}],[0],0,[0],[0],[0]],[[{"name":"27","rect":{"x":776,"y":231,"width":244,"height":237},"offset":{"x":-1,"y":-1.5},"originalSize":{"width":256,"height":248},"rotated":false,"capInsets":[0,0,0,0],"packable":true,"pixelsToUnit":100,"pivot":{"x":0.5,"y":0.5},"meshType":0}],[0],0,[0],[0],[0]],[[{"name":"star_4","rect":{"x":221,"y":670,"width":243,"height":88},"offset":{"x":0,"y":-1},"originalSize":{"width":253,"height":94},"rotated":false,"capInsets":[0,0,0,0],"packable":true,"pixelsToUnit":100,"pivot":{"x":0.5,"y":0.5},"meshType":0}],[0],0,[0],[0],[0]],[[{"name":"character_4","rect":{"x":3,"y":720,"width":212,"height":249},"offset":{"x":0,"y":-8.5},"originalSize":{"width":212,"height":266},"rotated":false,"capInsets":[0,0,0,0],"packable":true,"pixelsToUnit":100,"pivot":{"x":0.5,"y":0.5},"meshType":0}],[0],0,[0],[0],[0]],[[{"name":"powerSignal_0","rect":{"x":3,"y":3,"width":461,"height":458},"offset":{"x":0,"y":0},"originalSize":{"width":461,"height":458},"rotated":false,"capInsets":[0,0,0,0],"packable":true,"pixelsToUnit":100,"pivot":{"x":0.5,"y":0.5},"meshType":0}],[0],0,[0],[0],[0]],[[{"name":"item_1","rect":{"x":923,"y":720,"width":95,"height":98},"offset":{"x":6.5,"y":1},"originalSize":{"width":120,"height":120},"rotated":true,"capInsets":[0,0,0,0],"packable":true,"pixelsToUnit":100,"pivot":{"x":0.5,"y":0.5},"meshType":0}],[0],0,[0],[0],[0]],[[{"name":"26","rect":{"x":470,"y":519,"width":244,"height":236},"offset":{"x":-1,"y":-1},"originalSize":{"width":256,"height":248},"rotated":false,"capInsets":[0,0,0,0],"packable":true,"pixelsToUnit":100,"pivot":{"x":0.5,"y":0.5},"meshType":0}],[0],0,[0],[0],[0]],[[{"name":"item_16","rect":{"x":923,"y":821,"width":95,"height":98},"offset":{"x":-1.5,"y":2},"originalSize":{"width":120,"height":120},"rotated":true,"capInsets":[0,0,0,0],"packable":true,"pixelsToUnit":100,"pivot":{"x":0.5,"y":0.5},"meshType":0}],[0],0,[0],[0],[0]],[[{"name":"mountain_4","rect":{"x":470,"y":309,"width":280,"height":204},"offset":{"x":0,"y":0},"originalSize":{"width":280,"height":204},"rotated":false,"capInsets":[0,0,0,0],"packable":true,"pixelsToUnit":100,"pivot":{"x":0.5,"y":0.5},"meshType":0}],[0],0,[0],[0],[0]],[[{"name":"1","rect":{"x":221,"y":467,"width":243,"height":197},"offset":{"x":-56.5,"y":-15.5},"originalSize":{"width":500,"height":636},"rotated":false,"capInsets":[0,0,0,0],"packable":true,"pixelsToUnit":100,"pivot":{"x":0.5,"y":0.5},"meshType":0}],[0],0,[0],[0],[0]],[[{"name":"24","rect":{"x":444,"y":764,"width":241,"height":234},"offset":{"x":-0.5,"y":7},"originalSize":{"width":256,"height":248},"rotated":true,"capInsets":[0,0,0,0],"packable":true,"pixelsToUnit":100,"pivot":{"x":0.5,"y":0.5},"meshType":0}],[0],0,[0],[0],[0]],[[{"name":"character_2","rect":{"x":3,"y":467,"width":212,"height":239},"offset":{"x":0,"y":-13.5},"originalSize":{"width":212,"height":266},"rotated":false,"capInsets":[0,0,0,0],"packable":true,"pixelsToUnit":100,"pivot":{"x":0.5,"y":0.5},"meshType":0}],[0],0,[0],[0],[0]]]]
