[1,["16b8f692d@6c48a"],["_textureSource"],["cc.SpriteFrame"],0,[[[{"name":"frameBlue","rect":{"x":660,"y":828,"width":188,"height":188},"offset":{"x":0,"y":0},"originalSize":{"width":188,"height":188},"rotated":false,"capInsets":[0,0,0,0],"packable":true,"pixelsToUnit":100,"pivot":{"x":0.5,"y":0.5},"meshType":0}],[0],0,[0],[0],[0]],[[{"name":"button_startBattle","rect":{"x":466,"y":665,"width":188,"height":212},"offset":{"x":0,"y":0},"originalSize":{"width":188,"height":212},"rotated":false,"capInsets":[0,0,0,0],"packable":true,"pixelsToUnit":100,"pivot":{"x":0.5,"y":0.5},"meshType":0}],[0],0,[0],[0],[0]],[[{"name":"character_0","rect":{"x":493,"y":240,"width":212,"height":237},"offset":{"x":0,"y":-14.5},"originalSize":{"width":212,"height":266},"rotated":true,"capInsets":[0,0,0,0],"packable":true,"pixelsToUnit":100,"pivot":{"x":0.5,"y":0.5},"meshType":0}],[0],0,[0],[0],[0]],[[{"name":"11","rect":{"x":466,"y":458,"width":201,"height":203},"offset":{"x":4.5,"y":21.5},"originalSize":{"width":256,"height":248},"rotated":true,"capInsets":[0,0,0,0],"packable":true,"pixelsToUnit":100,"pivot":{"x":0.5,"y":0.5},"meshType":0}],[0],0,[0],[0],[0]],[[{"name":"20","rect":{"x":494,"y":3,"width":237,"height":231},"offset":{"x":0.5,"y":8.5},"originalSize":{"width":256,"height":248},"rotated":false,"capInsets":[0,0,0,0],"packable":true,"pixelsToUnit":100,"pivot":{"x":0.5,"y":0.5},"meshType":0}],[0],0,[0],[0],[0]],[[{"name":"16","rect":{"x":3,"y":241,"width":228,"height":220},"offset":{"x":2,"y":14},"originalSize":{"width":256,"height":248},"rotated":false,"capInsets":[0,0,0,0],"packable":true,"pixelsToUnit":100,"pivot":{"x":0.5,"y":0.5},"meshType":0}],[0],0,[0],[0],[0]],[[{"name":"item_0","rect":{"x":3,"y":922,"width":86,"height":159},"offset":{"x":-8,"y":-26.5},"originalSize":{"width":260,"height":280},"rotated":true,"capInsets":[0,0,0,0],"packable":true,"pixelsToUnit":100,"pivot":{"x":0.5,"y":0.5},"meshType":0}],[0],0,[0],[0],[0]],[[{"name":"18","rect":{"x":737,"y":238,"width":233,"height":228},"offset":{"x":0.5,"y":9},"originalSize":{"width":256,"height":248},"rotated":false,"capInsets":[0,0,0,0],"packable":true,"pixelsToUnit":100,"pivot":{"x":0.5,"y":0.5},"meshType":0}],[0],0,[0],[0],[0]],[[{"name":"21","rect":{"x":3,"y":3,"width":239,"height":232},"offset":{"x":0.5,"y":8},"originalSize":{"width":256,"height":248},"rotated":false,"capInsets":[0,0,0,0],"packable":true,"pixelsToUnit":100,"pivot":{"x":0.5,"y":0.5},"meshType":0}],[0],0,[0],[0],[0]],[[{"name":"40","rect":{"x":248,"y":3,"width":231,"height":240},"offset":{"x":10.5,"y":-2},"originalSize":{"width":256,"height":248},"rotated":true,"capInsets":[0,0,0,0],"packable":true,"pixelsToUnit":100,"pivot":{"x":0.5,"y":0.5},"meshType":0}],[0],0,[0],[0],[0]],[[{"name":"level","rect":{"x":200,"y":684,"width":190,"height":189},"offset":{"x":-5,"y":3.5},"originalSize":{"width":200,"height":200},"rotated":true,"capInsets":[0,0,0,0],"packable":true,"pixelsToUnit":100,"pivot":{"x":0.5,"y":0.5},"meshType":0}],[0],0,[0],[0],[0]],[[{"name":"15","rect":{"x":237,"y":458,"width":223,"height":220},"offset":{"x":2.5,"y":14},"originalSize":{"width":256,"height":248},"rotated":false,"capInsets":[0,0,0,0],"packable":true,"pixelsToUnit":100,"pivot":{"x":0.5,"y":0.5},"meshType":0}],[0],0,[0],[0],[0]],[[{"name":"item_5","rect":{"x":882,"y":647,"width":175,"height":127},"offset":{"x":5.5,"y":-2.5},"originalSize":{"width":200,"height":200},"rotated":true,"capInsets":[0,0,0,0],"packable":true,"pixelsToUnit":100,"pivot":{"x":0.5,"y":0.5},"meshType":0}],[0],0,[0],[0],[0]],[[{"name":"item_0","rect":{"x":660,"y":679,"width":175,"height":141},"offset":{"x":4.5,"y":-14.5},"originalSize":{"width":260,"height":280},"rotated":false,"capInsets":[0,0,0,0],"packable":true,"pixelsToUnit":100,"pivot":{"x":0.5,"y":0.5},"meshType":0}],[0],0,[0],[0],[0]],[[{"name":"tem_12","rect":{"x":462,"y":883,"width":169,"height":122},"offset":{"x":-5.5,"y":-6},"originalSize":{"width":200,"height":200},"rotated":false,"capInsets":[0,0,0,0],"packable":true,"pixelsToUnit":100,"pivot":{"x":0.5,"y":0.5},"meshType":0}],[0],0,[0],[0],[0]],[[{"name":"item_29","rect":{"x":854,"y":828,"width":155,"height":191},"offset":{"x":-9.5,"y":-17.5},"originalSize":{"width":260,"height":280},"rotated":false,"capInsets":[0,0,0,0],"packable":true,"pixelsToUnit":100,"pivot":{"x":0.5,"y":0.5},"meshType":0}],[0],0,[0],[0],[0]],[[{"name":"item_23","rect":{"x":314,"y":880,"width":139,"height":142},"offset":{"x":-14.5,"y":-39},"originalSize":{"width":260,"height":280},"rotated":true,"capInsets":[0,0,0,0],"packable":true,"pixelsToUnit":100,"pivot":{"x":0.5,"y":0.5},"meshType":0}],[0],0,[0],[0],[0]],[[{"name":"iconRadar","rect":{"x":168,"y":922,"width":140,"height":91},"offset":{"x":-1,"y":0.5},"originalSize":{"width":160,"height":160},"rotated":false,"capInsets":[0,0,0,0],"packable":true,"pixelsToUnit":100,"pivot":{"x":0.5,"y":0.5},"meshType":0}],[0],0,[0],[0],[0]],[[{"name":"item_0","rect":{"x":882,"y":472,"width":169,"height":133},"offset":{"x":-8.5,"y":-2.5},"originalSize":{"width":200,"height":200},"rotated":true,"capInsets":[0,0,0,0],"packable":true,"pixelsToUnit":100,"pivot":{"x":0.5,"y":0.5},"meshType":0}],[0],0,[0],[0],[0]],[[{"name":"45","rect":{"x":3,"y":683,"width":191,"height":233},"offset":{"x":19.5,"y":7.5},"originalSize":{"width":256,"height":248},"rotated":false,"capInsets":[0,0,0,0],"packable":true,"pixelsToUnit":100,"pivot":{"x":0.5,"y":0.5},"meshType":0}],[0],0,[0],[0],[0]],[[{"name":"character_2","rect":{"x":248,"y":240,"width":212,"height":239},"offset":{"x":0,"y":-13.5},"originalSize":{"width":212,"height":266},"rotated":true,"capInsets":[0,0,0,0],"packable":true,"pixelsToUnit":100,"pivot":{"x":0.5,"y":0.5},"meshType":0}],[0],0,[0],[0],[0]],[[{"name":"19","rect":{"x":737,"y":3,"width":235,"height":229},"offset":{"x":0.5,"y":8.5},"originalSize":{"width":256,"height":248},"rotated":false,"capInsets":[0,0,0,0],"packable":true,"pixelsToUnit":100,"pivot":{"x":0.5,"y":0.5},"meshType":0}],[0],0,[0],[0],[0]],[[{"name":"13","rect":{"x":3,"y":467,"width":213,"height":210},"offset":{"x":3.5,"y":19},"originalSize":{"width":256,"height":248},"rotated":false,"capInsets":[0,0,0,0],"packable":true,"pixelsToUnit":100,"pivot":{"x":0.5,"y":0.5},"meshType":0}],[0],0,[0],[0],[0]],[[{"name":"icon_taskSalvation","rect":{"x":675,"y":472,"width":201,"height":201},"offset":{"x":0,"y":0},"originalSize":{"width":201,"height":201},"rotated":false,"capInsets":[0,0,0,0],"packable":true,"pixelsToUnit":100,"pivot":{"x":0.5,"y":0.5},"meshType":0}],[0],0,[0],[0],[0]]]]
