[1,["1956bb941@6c48a"],["_textureSource"],["cc.SpriteFrame"],0,[[[{"name":"character_5","rect":{"x":809,"y":262,"width":212,"height":250},"offset":{"x":0,"y":-8},"originalSize":{"width":212,"height":266},"rotated":false,"capInsets":[0,0,0,0],"packable":true,"pixelsToUnit":100,"pivot":{"x":0.5,"y":0.5},"meshType":0}],[0],0,[0],[0],[0]],[[{"name":"mountain_2","rect":{"x":263,"y":773,"width":280,"height":204},"offset":{"x":0,"y":0},"originalSize":{"width":280,"height":204},"rotated":false,"capInsets":[0,0,0,0],"packable":true,"pixelsToUnit":100,"pivot":{"x":0.5,"y":0.5},"meshType":0}],[0],0,[0],[0],[0]],[[{"name":"item_2","rect":{"x":549,"y":772,"width":248,"height":249},"offset":{"x":4,"y":-31.5},"originalSize":{"width":420,"height":380},"rotated":false,"capInsets":[0,0,0,0],"packable":true,"pixelsToUnit":100,"pivot":{"x":0.5,"y":0.5},"meshType":0}],[0],0,[0],[0],[0]],[[{"name":"character_1","rect":{"x":809,"y":518,"width":212,"height":250},"offset":{"x":0,"y":-8},"originalSize":{"width":212,"height":266},"rotated":false,"capInsets":[0,0,0,0],"packable":true,"pixelsToUnit":100,"pivot":{"x":0.5,"y":0.5},"meshType":0}],[0],0,[0],[0],[0]],[[{"name":"icon_frame3","rect":{"x":245,"y":526,"width":241,"height":298},"offset":{"x":-0.5,"y":-3},"originalSize":{"width":266,"height":322},"rotated":true,"capInsets":[0,0,0,0],"packable":true,"pixelsToUnit":100,"pivot":{"x":0.5,"y":0.5},"meshType":0}],[0],0,[0],[0],[0]],[[{"name":"character_6","rect":{"x":809,"y":3,"width":212,"height":253},"offset":{"x":0,"y":-6.5},"originalSize":{"width":212,"height":266},"rotated":false,"capInsets":[0,0,0,0],"packable":true,"pixelsToUnit":100,"pivot":{"x":0.5,"y":0.5},"meshType":0}],[0],0,[0],[0],[0]],[[{"name":"32","rect":{"x":3,"y":774,"width":254,"height":245},"offset":{"x":1,"y":-0.5},"originalSize":{"width":256,"height":248},"rotated":false,"capInsets":[0,0,0,0],"packable":true,"pixelsToUnit":100,"pivot":{"x":0.5,"y":0.5},"meshType":0}],[0],0,[0],[0],[0]],[[{"name":"14","rect":{"x":803,"y":774,"width":218,"height":213},"offset":{"x":3,"y":17.5},"originalSize":{"width":256,"height":248},"rotated":false,"capInsets":[0,0,0,0],"packable":true,"pixelsToUnit":100,"pivot":{"x":0.5,"y":0.5},"meshType":0}],[0],0,[0],[0],[0]],[[{"name":"25","rect":{"x":3,"y":526,"width":242,"height":236},"offset":{"x":-1,"y":-1},"originalSize":{"width":256,"height":248},"rotated":true,"capInsets":[0,0,0,0],"packable":true,"pixelsToUnit":100,"pivot":{"x":0.5,"y":0.5},"meshType":0}],[0],0,[0],[0],[0]],[[{"name":"31","rect":{"x":549,"y":526,"width":254,"height":240},"offset":{"x":1,"y":-2},"originalSize":{"width":256,"height":248},"rotated":false,"capInsets":[0,0,0,0],"packable":true,"pixelsToUnit":100,"pivot":{"x":0.5,"y":0.5},"meshType":0}],[0],0,[0],[0],[0]]]]
