[1,["15e2fcf33@6c48a"],["_textureSource"],["cc.SpriteFrame"],0,[[[{"name":"item_7","rect":{"x":3,"y":811,"width":192,"height":134},"offset":{"x":-14,"y":-34},"originalSize":{"width":350,"height":280},"rotated":false,"capInsets":[0,0,0,0],"packable":true,"pixelsToUnit":100,"pivot":{"x":0.5,"y":0.5},"meshType":0}],[0],0,[0],[0],[0]],[[{"name":"item_19","rect":{"x":881,"y":412,"width":140,"height":131},"offset":{"x":1,"y":-27.5},"originalSize":{"width":260,"height":280},"rotated":false,"capInsets":[0,0,0,0],"packable":true,"pixelsToUnit":100,"pivot":{"x":0.5,"y":0.5},"meshType":0}],[0],0,[0],[0],[0]],[[{"name":"item_24","rect":{"x":895,"y":3,"width":126,"height":131},"offset":{"x":0,"y":-26.5},"originalSize":{"width":260,"height":280},"rotated":false,"capInsets":[0,0,0,0],"packable":true,"pixelsToUnit":100,"pivot":{"x":0.5,"y":0.5},"meshType":0}],[0],0,[0],[0],[0]],[[{"name":"item_6","rect":{"x":733,"y":824,"width":163,"height":138},"offset":{"x":-10.5,"y":-33},"originalSize":{"width":350,"height":280},"rotated":false,"capInsets":[0,0,0,0],"packable":true,"pixelsToUnit":100,"pivot":{"x":0.5,"y":0.5},"meshType":0}],[0],0,[0],[0],[0]],[[{"name":"item_10","rect":{"x":583,"y":819,"width":144,"height":138},"offset":{"x":-11,"y":-24},"originalSize":{"width":350,"height":280},"rotated":false,"capInsets":[0,0,0,0],"packable":true,"pixelsToUnit":100,"pivot":{"x":0.5,"y":0.5},"meshType":0}],[0],0,[0],[0],[0]],[[{"name":"item_11","rect":{"x":301,"y":674,"width":132,"height":143},"offset":{"x":-4,"y":-12.5},"originalSize":{"width":260,"height":280},"rotated":true,"capInsets":[0,0,0,0],"packable":true,"pixelsToUnit":100,"pivot":{"x":0.5,"y":0.5},"meshType":0}],[0],0,[0],[0],[0]],[[{"name":"button_2","rect":{"x":890,"y":273,"width":130,"height":133},"offset":{"x":0,"y":0},"originalSize":{"width":130,"height":133},"rotated":false,"capInsets":[0,0,0,0],"packable":true,"pixelsToUnit":100,"pivot":{"x":0.5,"y":0.5},"meshType":0}],[0],0,[0],[0],[0]],[[{"name":"item_21","rect":{"x":162,"y":132,"width":131,"height":126},"offset":{"x":4.5,"y":-16},"originalSize":{"width":260,"height":280},"rotated":false,"capInsets":[0,0,0,0],"packable":true,"pixelsToUnit":100,"pivot":{"x":0.5,"y":0.5},"meshType":0}],[0],0,[0],[0],[0]],[[{"name":"CaseAirTech","rect":{"x":283,"y":537,"width":153,"height":131},"offset":{"x":3.5,"y":4.5},"originalSize":{"width":160,"height":160},"rotated":false,"capInsets":[0,0,0,0],"packable":true,"pixelsToUnit":100,"pivot":{"x":0.5,"y":0.5},"meshType":0}],[0],0,[0],[0],[0]],[[{"name":"item_3","rect":{"x":442,"y":537,"width":145,"height":131},"offset":{"x":-9.5,"y":-6.5},"originalSize":{"width":200,"height":200},"rotated":false,"capInsets":[0,0,0,0],"packable":true,"pixelsToUnit":100,"pivot":{"x":0.5,"y":0.5},"meshType":0}],[0],0,[0],[0],[0]],[[{"name":"item_26","rect":{"x":3,"y":532,"width":131,"height":135},"offset":{"x":9.5,"y":-16.5},"originalSize":{"width":260,"height":280},"rotated":true,"capInsets":[0,0,0,0],"packable":true,"pixelsToUnit":100,"pivot":{"x":0.5,"y":0.5},"meshType":0}],[0],0,[0],[0],[0]],[[{"name":"item_7","rect":{"x":618,"y":3,"width":125,"height":127},"offset":{"x":-1.5,"y":-18.5},"originalSize":{"width":260,"height":280},"rotated":true,"capInsets":[0,0,0,0],"packable":true,"pixelsToUnit":100,"pivot":{"x":0.5,"y":0.5},"meshType":0}],[0],0,[0],[0],[0]],[[{"name":"item_18","rect":{"x":580,"y":134,"width":127,"height":130},"offset":{"x":6.5,"y":-2},"originalSize":{"width":260,"height":280},"rotated":true,"capInsets":[0,0,0,0],"packable":true,"pixelsToUnit":100,"pivot":{"x":0.5,"y":0.5},"meshType":0}],[0],0,[0],[0],[0]],[[{"name":"CaseTech","rect":{"x":716,"y":134,"width":154,"height":127},"offset":{"x":-3,"y":0.5},"originalSize":{"width":160,"height":160},"rotated":false,"capInsets":[0,0,0,0],"packable":true,"pixelsToUnit":100,"pivot":{"x":0.5,"y":0.5},"meshType":0}],[0],0,[0],[0],[0]],[[{"name":"CaseChemicalTech","rect":{"x":593,"y":544,"width":154,"height":131},"offset":{"x":-3,"y":-0.5},"originalSize":{"width":160,"height":160},"rotated":false,"capInsets":[0,0,0,0],"packable":true,"pixelsToUnit":100,"pivot":{"x":0.5,"y":0.5},"meshType":0}],[0],0,[0],[0],[0]],[[{"name":"item_0","rect":{"x":173,"y":265,"width":128,"height":239},"offset":{"x":-7,"y":-45.5},"originalSize":{"width":390,"height":420},"rotated":true,"capInsets":[0,0,0,0],"packable":true,"pixelsToUnit":100,"pivot":{"x":0.5,"y":0.5},"meshType":0}],[0],0,[0],[0],[0]],[[{"name":"item_5","rect":{"x":751,"y":3,"width":138,"height":125},"offset":{"x":16,"y":-9.5},"originalSize":{"width":200,"height":200},"rotated":false,"capInsets":[0,0,0,0],"packable":true,"pixelsToUnit":100,"pivot":{"x":0.5,"y":0.5},"meshType":0}],[0],0,[0],[0],[0]],[[{"name":"item_7","rect":{"x":385,"y":818,"width":192,"height":135},"offset":{"x":14,"y":-33.5},"originalSize":{"width":350,"height":280},"rotated":false,"capInsets":[0,0,0,0],"packable":true,"pixelsToUnit":100,"pivot":{"x":0.5,"y":0.5},"meshType":0}],[0],0,[0],[0],[0]],[[{"name":"item_4","rect":{"x":144,"y":535,"width":131,"height":133},"offset":{"x":1.5,"y":-1.5},"originalSize":{"width":200,"height":200},"rotated":true,"capInsets":[0,0,0,0],"packable":true,"pixelsToUnit":100,"pivot":{"x":0.5,"y":0.5},"meshType":0}],[0],0,[0],[0],[0]],[[{"name":"item_8","rect":{"x":562,"y":267,"width":178,"height":128},"offset":{"x":1,"y":7},"originalSize":{"width":200,"height":200},"rotated":false,"capInsets":[0,0,0,0],"packable":true,"pixelsToUnit":100,"pivot":{"x":0.5,"y":0.5},"meshType":0}],[0],0,[0],[0],[0]],[[{"name":"item_11","rect":{"x":753,"y":549,"width":131,"height":138},"offset":{"x":-1.5,"y":-2},"originalSize":{"width":200,"height":200},"rotated":true,"capInsets":[0,0,0,0],"packable":true,"pixelsToUnit":100,"pivot":{"x":0.5,"y":0.5},"meshType":0}],[0],0,[0],[0],[0]],[[{"name":"item_4","rect":{"x":299,"y":133,"width":136,"height":126},"offset":{"x":1,"y":-22},"originalSize":{"width":260,"height":280},"rotated":false,"capInsets":[0,0,0,0],"packable":true,"pixelsToUnit":100,"pivot":{"x":0.5,"y":0.5},"meshType":0}],[0],0,[0],[0],[0]],[[{"name":"CaseFlowerTech","rect":{"x":590,"y":681,"width":141,"height":132},"offset":{"x":-0.5,"y":-1},"originalSize":{"width":160,"height":160},"rotated":false,"capInsets":[0,0,0,0],"packable":true,"pixelsToUnit":100,"pivot":{"x":0.5,"y":0.5},"meshType":0}],[0],0,[0],[0],[0]],[[{"name":"button_3","rect":{"x":147,"y":399,"width":130,"height":133},"offset":{"x":0,"y":0},"originalSize":{"width":130,"height":133},"rotated":true,"capInsets":[0,0,0,0],"packable":true,"pixelsToUnit":100,"pivot":{"x":0.5,"y":0.5},"meshType":0}],[0],0,[0],[0],[0]],[[{"name":"item_12","rect":{"x":201,"y":812,"width":178,"height":134},"offset":{"x":6,"y":-4},"originalSize":{"width":200,"height":200},"rotated":false,"capInsets":[0,0,0,0],"packable":true,"pixelsToUnit":100,"pivot":{"x":0.5,"y":0.5},"meshType":0}],[0],0,[0],[0],[0]],[[{"name":"item_21","rect":{"x":450,"y":674,"width":138,"height":134},"offset":{"x":18,"y":-23},"originalSize":{"width":260,"height":280},"rotated":true,"capInsets":[0,0,0,0],"packable":true,"pixelsToUnit":100,"pivot":{"x":0.5,"y":0.5},"meshType":0}],[0],0,[0],[0],[0]],[[{"name":"item_20","rect":{"x":441,"y":133,"width":126,"height":133},"offset":{"x":-3,"y":-32.5},"originalSize":{"width":260,"height":280},"rotated":true,"capInsets":[0,0,0,0],"packable":true,"pixelsToUnit":100,"pivot":{"x":0.5,"y":0.5},"meshType":0}],[0],0,[0],[0],[0]],[[{"name":"button_1","rect":{"x":286,"y":400,"width":130,"height":133},"offset":{"x":0,"y":0},"originalSize":{"width":130,"height":133},"rotated":true,"capInsets":[0,0,0,0],"packable":true,"pixelsToUnit":100,"pivot":{"x":0.5,"y":0.5},"meshType":0}],[0],0,[0],[0],[0]],[[{"name":"CaseMarineTech","rect":{"x":3,"y":672,"width":140,"height":131},"offset":{"x":0,"y":0.5},"originalSize":{"width":160,"height":160},"rotated":false,"capInsets":[0,0,0,0],"packable":true,"pixelsToUnit":100,"pivot":{"x":0.5,"y":0.5},"meshType":0}],[0],0,[0],[0],[0]],[[{"name":"item_17","rect":{"x":737,"y":686,"width":148,"height":132},"offset":{"x":-1,"y":-36},"originalSize":{"width":260,"height":280},"rotated":false,"capInsets":[0,0,0,0],"packable":true,"pixelsToUnit":100,"pivot":{"x":0.5,"y":0.5},"meshType":0}],[0],0,[0],[0],[0]],[[{"name":"CaseOverlandTech","rect":{"x":425,"y":401,"width":153,"height":130},"offset":{"x":-3.5,"y":-1},"originalSize":{"width":160,"height":160},"rotated":false,"capInsets":[0,0,0,0],"packable":true,"pixelsToUnit":100,"pivot":{"x":0.5,"y":0.5},"meshType":0}],[0],0,[0],[0],[0]],[[{"name":"item_8","rect":{"x":876,"y":140,"width":144,"height":127},"offset":{"x":16,"y":-10.5},"originalSize":{"width":264,"height":280},"rotated":false,"capInsets":[0,0,0,0],"packable":true,"pixelsToUnit":100,"pivot":{"x":0.5,"y":0.5},"meshType":0}],[0],0,[0],[0],[0]],[[{"name":"item_29","rect":{"x":3,"y":3,"width":123,"height":134},"offset":{"x":-7.5,"y":-38},"originalSize":{"width":260,"height":280},"rotated":true,"capInsets":[0,0,0,0],"packable":true,"pixelsToUnit":100,"pivot":{"x":0.5,"y":0.5},"meshType":0}],[0],0,[0],[0],[0]],[[{"name":"item_22","rect":{"x":418,"y":265,"width":129,"height":138},"offset":{"x":6.5,"y":-25},"originalSize":{"width":260,"height":280},"rotated":true,"capInsets":[0,0,0,0],"packable":true,"pixelsToUnit":100,"pivot":{"x":0.5,"y":0.5},"meshType":0}],[0],0,[0],[0],[0]],[[{"name":"planBuildBarrackOverland","rect":{"x":303,"y":3,"width":154,"height":124},"offset":{"x":-1,"y":-2.5},"originalSize":{"width":160,"height":161},"rotated":false,"capInsets":[0,0,0,0],"packable":true,"pixelsToUnit":100,"pivot":{"x":0.5,"y":0.5},"meshType":0}],[0],0,[0],[0],[0]],[[{"name":"item_18","rect":{"x":463,"y":3,"width":149,"height":124},"offset":{"x":3.5,"y":-56},"originalSize":{"width":260,"height":280},"rotated":false,"capInsets":[0,0,0,0],"packable":true,"pixelsToUnit":100,"pivot":{"x":0.5,"y":0.5},"meshType":0}],[0],0,[0],[0],[0]],[[{"name":"item_16","rect":{"x":746,"y":273,"width":129,"height":138},"offset":{"x":-1.5,"y":-29},"originalSize":{"width":260,"height":280},"rotated":true,"capInsets":[0,0,0,0],"packable":true,"pixelsToUnit":100,"pivot":{"x":0.5,"y":0.5},"meshType":0}],[0],0,[0],[0],[0]],[[{"name":"tem_11","rect":{"x":3,"y":264,"width":164,"height":127},"offset":{"x":-1,"y":-3.5},"originalSize":{"width":200,"height":200},"rotated":false,"capInsets":[0,0,0,0],"packable":true,"pixelsToUnit":100,"pivot":{"x":0.5,"y":0.5},"meshType":0}],[0],0,[0],[0],[0]],[[{"name":"item_6","rect":{"x":3,"y":132,"width":153,"height":125},"offset":{"x":22.5,"y":-18.5},"originalSize":{"width":260,"height":280},"rotated":false,"capInsets":[0,0,0,0],"packable":true,"pixelsToUnit":100,"pivot":{"x":0.5,"y":0.5},"meshType":0}],[0],0,[0],[0],[0]],[[{"name":"item_17","rect":{"x":149,"y":674,"width":146,"height":131},"offset":{"x":13,"y":-19.5},"originalSize":{"width":260,"height":280},"rotated":false,"capInsets":[0,0,0,0],"packable":true,"pixelsToUnit":100,"pivot":{"x":0.5,"y":0.5},"meshType":0}],[0],0,[0],[0],[0]],[[{"name":"button_0","rect":{"x":584,"y":401,"width":130,"height":133},"offset":{"x":0,"y":0},"originalSize":{"width":130,"height":133},"rotated":true,"capInsets":[0,0,0,0],"packable":true,"pixelsToUnit":100,"pivot":{"x":0.5,"y":0.5},"meshType":0}],[0],0,[0],[0],[0]],[[{"name":"item_22","rect":{"x":723,"y":408,"width":152,"height":130},"offset":{"x":1.5,"y":-37},"originalSize":{"width":259,"height":280},"rotated":false,"capInsets":[0,0,0,0],"packable":true,"pixelsToUnit":100,"pivot":{"x":0.5,"y":0.5},"meshType":0}],[0],0,[0],[0],[0]],[[{"name":"planMergeBarrackOverland","rect":{"x":143,"y":3,"width":154,"height":123},"offset":{"x":0,"y":-11.5},"originalSize":{"width":160,"height":160},"rotated":false,"capInsets":[0,0,0,0],"packable":true,"pixelsToUnit":100,"pivot":{"x":0.5,"y":0.5},"meshType":0}],[0],0,[0],[0],[0]],[[{"name":"item_25","rect":{"x":3,"y":397,"width":129,"height":138},"offset":{"x":11.5,"y":-43},"originalSize":{"width":260,"height":280},"rotated":true,"capInsets":[0,0,0,0],"packable":true,"pixelsToUnit":100,"pivot":{"x":0.5,"y":0.5},"meshType":0}],[0],0,[0],[0],[0]]]]
